openstack_odooclient/__init__.py
openstack_odooclient/client.py
openstack_odooclient/exceptions.py
openstack_odooclient/py.typed
openstack_odooclient/util.py
openstack_odooclient/base/__init__.py
openstack_odooclient/base/client.py
openstack_odooclient/base/record/__init__.py
openstack_odooclient/base/record/base.py
openstack_odooclient/base/record/types.py
openstack_odooclient/base/record_manager/__init__.py
openstack_odooclient/base/record_manager/base.py
openstack_odooclient/base/record_manager/protocol.py
openstack_odooclient/base/record_manager/types.py
openstack_odooclient/managers/__init__.py
openstack_odooclient/managers/account_move.py
openstack_odooclient/managers/account_move_line.py
openstack_odooclient/managers/attachment.py
openstack_odooclient/managers/company.py
openstack_odooclient/managers/credit.py
openstack_odooclient/managers/credit_transaction.py
openstack_odooclient/managers/credit_type.py
openstack_odooclient/managers/currency.py
openstack_odooclient/managers/customer_group.py
openstack_odooclient/managers/grant.py
openstack_odooclient/managers/grant_type.py
openstack_odooclient/managers/partner.py
openstack_odooclient/managers/partner_category.py
openstack_odooclient/managers/pricelist.py
openstack_odooclient/managers/product.py
openstack_odooclient/managers/product_category.py
openstack_odooclient/managers/project.py
openstack_odooclient/managers/project_contact.py
openstack_odooclient/managers/referral_code.py
openstack_odooclient/managers/reseller.py
openstack_odooclient/managers/reseller_tier.py
openstack_odooclient/managers/sale_order.py
openstack_odooclient/managers/sale_order_line.py
openstack_odooclient/managers/support_subscription.py
openstack_odooclient/managers/support_subscription_type.py
openstack_odooclient/managers/tax.py
openstack_odooclient/managers/tax_group.py
openstack_odooclient/managers/term_discount.py
openstack_odooclient/managers/trial.py
openstack_odooclient/managers/uom.py
openstack_odooclient-0.2.2.dist-info/licenses/LICENSE
openstack_odooclient-0.2.2.dist-info/METADATA
openstack_odooclient-0.2.2.dist-info/WHEEL
openstack_odooclient-0.2.2.dist-info/top_level.txt
openstack_odooclient-0.2.2.dist-info/RECORD
