Metadata-Version: 2.4
Name: openstack-odooclient
Version: 0.2.2
Summary: Python client library for Odoo and the OpenStack integration add-on.
Author-email: Callum Dickinson <callum.dickinson@catalystcloud.nz>
License-Expression: Apache-2.0
Project-URL: Homepage, https://catalyst-cloud.github.io/python-openstack-odooclient
Project-URL: Documentation, https://catalyst-cloud.github.io/python-openstack-odooclient
Project-URL: Repository, https://github.com/catalyst-cloud/python-openstack-odooclient
Project-URL: Issues, https://github.com/catalyst-cloud/python-openstack-odooclient/issues
Project-URL: Changelog, https://catalyst-cloud.github.io/python-openstack-odooclient/latest/changelog.html
Keywords: openstack,odoo,erp,billing
Classifier: Development Status :: 4 - Beta
Classifier: Intended Audience :: Developers
Classifier: Natural Language :: English
Classifier: Operating System :: OS Independent
Classifier: Programming Language :: Python :: 3
Classifier: Programming Language :: Python :: 3.10
Classifier: Programming Language :: Python :: 3.11
Classifier: Programming Language :: Python :: 3.12
Classifier: Programming Language :: Python :: 3.13
Classifier: Programming Language :: Python :: 3.14
Classifier: Topic :: Software Development :: Libraries
Classifier: Typing :: Typed
Requires-Python: >=3.10
License-File: LICENSE
Requires-Dist: odoorpc>=0.10.1
Requires-Dist: packaging
Requires-Dist: typing-extensions>=4.12.2
Dynamic: license-file
